mfoxadc/__main__.py
mfoxadc-1.0.0a2.dist-info/METADATA
mfoxadc-1.0.0a2.dist-info/WHEEL
mfoxadc-1.0.0a2.dist-info/entry_points.txt
mfoxadc-1.0.0a2.dist-info/RECORD
