Metadata-Version: 2.3
Name: mfoxadc
Version: 1.0.0a2
Summary: A tool for encoding LuckFox ADC values for sending as Meshtastic UDP messages
License: GPL-3.0-only
Author: Ben Lipsey
Author-email: ben@pdxlocations.com
Requires-Python: >=3.9,<3.14
Classifier: License :: OSI Approved :: GNU General Public License v3 (GPLv3)
Classifier: Programming Language :: Python :: 3
Classifier: Programming Language :: Python :: 3.9
Classifier: Programming Language :: Python :: 3.10
Classifier: Programming Language :: Python :: 3.11
Classifier: Programming Language :: Python :: 3.12
Classifier: Programming Language :: Python :: 3.13
Project-URL: Homepage, https://github.com/pdxlocations/mfoxadc
Project-URL: Issues, https://github.com/pdxlocations/mfoxadc/issues
